cliper_cli/__init__.py
cliper_cli/__main__.py
commands/__init__.py
commands/access.py
commands/list_contents.py
commands/remove.py
commands/save.py
commands/search.py
helpers/__init__.py
helpers/check_clipboard_empty.py
helpers/clipboard_contents_model.py
helpers/error_handling_for_save.py
helpers/json.py
helpers/show_clipboard_contents.py
helpers/sort.py
cliper-1.4.2.dist-info/METADATA
cliper-1.4.2.dist-info/WHEEL
cliper-1.4.2.dist-info/entry_points.txt
cliper-1.4.2.dist-info/top_level.txt
cliper-1.4.2.dist-info/RECORD
