Metadata-Version: 2.4
Name: cliper
Version: 1.4.2
Summary: a clipboard manager tool to save important things with labels
Author-email: Omar Arabi <omarbuisness7@gmail.com>
Requires-Python: >=3.13
Requires-Dist: click<9,>=8.2.1
Requires-Dist: colorama<1,>=0.4.6
Requires-Dist: fuzzywuzzy<1,>=0.18.0
Requires-Dist: pyperclip<2,>=1.9.0
Requires-Dist: python-levenshtein<1,>=0.27.1
Requires-Dist: tabulate<1,>=0.9.0
